emailtoolspython/__init__.py
emailtoolspython/util/__init__.py
emailtoolspython/util/agents.py
emailtoolspython/util/seleniumdriver.py
emailtoolspython-0.4.5.dist-info/METADATA
emailtoolspython-0.4.5.dist-info/WHEEL
emailtoolspython-0.4.5.dist-info/top_level.txt
emailtoolspython-0.4.5.dist-info/RECORD
