Metadata-Version: 2.1
Name: emailtoolspython
Version: 0.4.5
Summary: A series of methods to help you work with validation and extraction of e-mails
Home-page: https://github.com/EvertonTomalok/emailtoolspython
Author: Everton Tomalok
Author-email: evertontomalok123@gmail.com
License: MIT
Download-URL: https://github.com/EvertonTomalok/emailtoolspython/archive/master.zip
Keywords: email,emails,tool,tools
Platform: UNKNOWN
Classifier: Programming Language :: Python :: 3
Classifier: Programming Language :: Python :: 3.6
Classifier: License :: OSI Approved :: MIT License
Classifier: Operating System :: OS Independent
Requires-Dist: requests (>=2.19.1)
Requires-Dist: beautifulsoup4 (>=4.4.0)
Requires-Dist: selenium
Requires-Dist: dnspython
Requires-Dist: tldextract
